[1,["9014KcLNNI3r7XYl3ZG2Qa"],["_effectAsset"],[["cc.Material",["_name","_techniqueData"],2,11]],[[0,0,1,2]],[[0,"SpineOutLine",[{"2":{"props":{"outlineWidth":10},"defines":{"USE_TEXTURE":true}},"4":{"props":{},"defines":{"USE_TEXTURE":true}},"8":{"props":{},"defines":{}}},"0",11,[{"defines":{"USE_TEXTURE":true}},"props",11,[{"outlineWidth":10},"outlineColor",8,[4,4294967295]]],"1",11,[{"defines":{"USE_TEXTURE":true}},"props",11,[{"outlineWidth":10},"outlineColor",8,[4,4294967295]]],"3",11,[{"defines":{"USE_TEXTURE":true}},"props",11,[{},"outlineColor",8,[4,4294967295]]]]]],0,0,[0],[0],[0]]